wifi_tool/__init__.py
wifi_tool/wifi_tool.py
micropython_wifi_tool-0.0.1.dist-info/LICENSE
micropython_wifi_tool-0.0.1.dist-info/METADATA
micropython_wifi_tool-0.0.1.dist-info/WHEEL
micropython_wifi_tool-0.0.1.dist-info/top_level.txt
micropython_wifi_tool-0.0.1.dist-info/RECORD
