Metadata-Version: 2.1
Name: micropython-wifi-tool
Version: 0.0.1
Summary: A wifi tool for micropython
Home-page: https://github.com/SSBun/micropython-wifi-tool
Author: shilin cai
Author-email: caishilin@yahoo.com
License: UNKNOWN
Platform: UNKNOWN
Classifier: Programming Language :: Python :: 3
Classifier: License :: OSI Approved :: MIT License
Classifier: Operating System :: OS Independent
Requires-Python: >=3.6
